shellcoderunneraes.py
shellcoderunner_aes-1.1.0.dist-info/licenses/LICENSE
shellcoderunner_aes-1.1.0.dist-info/METADATA
shellcoderunner_aes-1.1.0.dist-info/WHEEL
shellcoderunner_aes-1.1.0.dist-info/entry_points.txt
shellcoderunner_aes-1.1.0.dist-info/top_level.txt
shellcoderunner_aes-1.1.0.dist-info/RECORD
