Metadata-Version: 2.4
Name: shellcoderunner-aes
Version: 1.1.0
Summary: AES-based shellcode loader generator for Windows security research
Author: PaiN05
License: MIT
Classifier: Programming Language :: Python :: 3
Classifier: Topic :: Security
Classifier: Intended Audience :: Developers
Classifier: Intended Audience :: Information Technology
License-File: LICENSE
Requires-Dist: pycryptodome
Dynamic: author
Dynamic: classifier
Dynamic: description
Dynamic: description-content-type
Dynamic: license
Dynamic: license-file
Dynamic: requires-dist
Dynamic: summary
